datahold/__init__.py
datahold/_utils/Cfg.py
datahold/_utils/__init__.py
datahold/_utils/cfg.toml
datahold/_utils/deco/__init__.py
datahold/_utils/deco/dataDeco.py
datahold/_utils/deco/funcDeco.py
datahold/_utils/deco/initDeco.py
datahold/_utils/deco/wrapping.py
datahold/core/DataABC.py
datahold/core/DataDict.py
datahold/core/DataList.py
datahold/core/DataSet.py
datahold/core/HoldABC.py
datahold/core/HoldDict.py
datahold/core/HoldList.py
datahold/core/HoldSet.py
datahold/core/OkayABC.py
datahold/core/OkayDict.py
datahold/core/OkayList.py
datahold/core/OkaySet.py
datahold/core/__init__.py
datahold/tests/__init__.py
datahold/tests/test_okay.py
datahold-2.0.5.dist-info/licenses/LICENSE.txt
datahold-2.0.5.dist-info/METADATA
datahold-2.0.5.dist-info/WHEEL
datahold-2.0.5.dist-info/top_level.txt
datahold-2.0.5.dist-info/RECORD
