Metadata-Version: 2.4
Name: datahold
Version: 2.0.5
Summary: This project wraps common mutable datastructures for inheritance with modification.
Author-email: Johannes <johannes.programming@gmail.com>
License: The MIT License (MIT)
Project-URL: Download, https://pypi.org/project/datahold/#files
Project-URL: Index, https://pypi.org/project/datahold/
Project-URL: Source, https://github.com/johannes-programming/datahold/
Project-URL: Website, http://datahold.johannes-programming.online/
Classifier: Development Status :: 5 - Production/Stable
Classifier: Intended Audience :: Developers
Classifier: License :: OSI Approved :: MIT License
Classifier: Natural Language :: English
Classifier: Operating System :: OS Independent
Classifier: Programming Language :: Python
Classifier: Programming Language :: Python :: 3
Classifier: Programming Language :: Python :: 3 :: Only
Classifier: Typing :: Typed
Requires-Python: >=3.11
License-File: LICENSE.txt
Requires-Dist: datarepr<2,>=1.0
Requires-Dist: frozendict<3,>=2.4.6
Requires-Dist: scaevola<2,>=1.0.11
Requires-Dist: setdoc<2,>=1.2.4
Requires-Dist: unhash<2,>=1.0
Dynamic: license-file
